kodipydent/KodiClient.py
kodipydent/__init__.py
kodipydent/rpctohive.py
kodipydent-0.3.dist-info/DESCRIPTION.rst
kodipydent-0.3.dist-info/METADATA
kodipydent-0.3.dist-info/RECORD
kodipydent-0.3.dist-info/WHEEL
kodipydent-0.3.dist-info/metadata.json
kodipydent-0.3.dist-info/top_level.txt
