Metadata-Version: 2.0
Name: kodipydent
Version: 0.3
Summary: UNKNOWN
Home-page: https://github.com/haikuginger/kodipydent
Author: Jesse Shapiro
Author-email: jesse@jesseshapiro.net
License: UNKNOWN
Keywords: Kodi JSON-RPC JSONRPC RPC JSON client XBMC
Platform: UNKNOWN
Classifier: License :: OSI Approved :: MIT License
Classifier: Programming Language :: Python
Classifier: Programming Language :: Python :: 2
Classifier: Programming Language :: Python :: 2.7
Classifier: Programming Language :: Python :: 3
Classifier: Programming Language :: Python :: 3.4
Classifier: Programming Language :: Python :: 3.5
Requires-Dist: beekeeper (==0.9.2)
